energy_monitor/__init__.py
energy_monitor/cpu_percent.py
energy_monitor/dash_app.py
energy_monitor/powergadget_wrapper.py
energy_monitor/train_mnist.py
energy_monitor/utils.py
energy_monitor-0.7.5.data/scripts/display-energy
energy_monitor-0.7.5.dist-info/METADATA
energy_monitor-0.7.5.dist-info/WHEEL
energy_monitor-0.7.5.dist-info/top_level.txt
energy_monitor-0.7.5.dist-info/RECORD
